[
  {
    "inputs": [],
    "stateMutability": "nonpayable",
    "type": "constructor"
  },
  {
    "inputs": [],
    "name": "owner",
    "outputs": [
      {
        "internalType": "address",
        "name": "",
        "type": "address"
      }
    ],
    "stateMutability": "view",
    "type": "function"
  },
  {
    "inputs": [
      {
        "internalType": "address[]",
        "name": "pools",
        "type": "address[]"
      },
      {
        "internalType": "bool[]",
        "name": "zeroForOne",
        "type": "bool[]"
      },
      {
        "internalType": "address[]",
        "name": "tokens",
        "type": "address[]"
      },
      {
        "internalType": "uint256",
        "name": "amountIn",
        "type": "uint256"
      }
    ],
    "name": "startArbitrage",
    "outputs": [],
    "stateMutability": "nonpayable",
    "type": "function"
  },
  {
    "inputs": [
      {
        "internalType": "int256",
        "name": "amount0Delta",
        "type": "int256"
      },
      {
        "internalType": "int256",
        "name": "amount1Delta",
        "type": "int256"
      },
      {
        "internalType": "bytes",
        "name": "data",
        "type": "bytes"
      }
    ],
    "name": "uniswapV3SwapCallback",
    "outputs": [],
    "stateMutability": "nonpayable",
    "type": "function"
  },
  {
    "inputs": [
      {
        "internalType": "address",
        "name": "token",
        "type": "address"
      }
    ],
    "name": "withdraw",
    "outputs": [],
    "stateMutability": "nonpayable",
    "type": "function"
  }
]